setup.py
Products/__init__.py
Products.Plone3Cleaners.egg-info/PKG-INFO
Products.Plone3Cleaners.egg-info/SOURCES.txt
Products.Plone3Cleaners.egg-info/dependency_links.txt
Products.Plone3Cleaners.egg-info/entry_points.txt
Products.Plone3Cleaners.egg-info/namespace_packages.txt
Products.Plone3Cleaners.egg-info/not-zip-safe
Products.Plone3Cleaners.egg-info/requires.txt
Products.Plone3Cleaners.egg-info/top_level.txt
Products/Plone3Cleaners/HISTORY.txt
Products/Plone3Cleaners/README.txt
Products/Plone3Cleaners/__init__.py
Products/Plone3Cleaners/configure.zcml
Products/Plone3Cleaners/find_local_sites.pt
Products/Plone3Cleaners/localsites.py
Products/Plone3Cleaners/managesite.pt
Products/Plone3Cleaners/portal_factory.pt
Products/Plone3Cleaners/portal_factory.py
docs/INSTALL.txt
docs/LICENSE.GPL
docs/LICENSE.txt