Metadata-Version: 1.0
Name: Products.Plone3Cleaners
Version: 1.1
Summary: Cleanup after migration from Plone 2.5 to 3
Home-page: UNKNOWN
Author: Zest Software
Author-email: m.van.rees@zestsoftware.nl
License: GPL
Platform: UNKNOWN
Classifier: Framework :: Plone
Classifier: Programming Language :: Python
Classifier: Topic :: Software Development :: Libraries :: Python Modules
